<?xml version="1.0" encoding="UTF-8"?>
<!DOCTYPE QtCreatorCMakeTools>
<!-- Written by QtCreator 4.8.2, 2020-05-03T19:52:31. -->
<qtcreator>
 <data>
  <variable>CMakeTools.0</variable>
  <valuemap type="QVariantMap">
   <value type="bool" key="AutoCreateBuildDirectory">false</value>
   <value type="bool" key="AutoDetected">true</value>
   <value type="bool" key="AutoRun">true</value>
   <value type="QString" key="Binary">/usr/bin/cmake</value>
   <value type="QString" key="DisplayName">System CMake at /usr/bin/cmake</value>
   <value type="QString" key="Id">{fafbf8bd-e2ca-4e83-b12f-100f4196f38a}</value>
  </valuemap>
 </data>
 <data>
  <variable>CMakeTools.1</variable>
  <valuemap type="QVariantMap">
   <value type="bool" key="AutoCreateBuildDirectory">false</value>
   <value type="bool" key="AutoDetected">true</value>
   <value type="bool" key="AutoRun">true</value>
   <value type="QString" key="Binary">/bin/cmake</value>
   <value type="QString" key="DisplayName">System CMake at /bin/cmake</value>
   <value type="QString" key="Id">{87b8b0d4-b0d9-4ee1-8f0d-23a6952e2b11}</value>
  </valuemap>
 </data>
 <data>
  <variable>CMakeTools.Count</variable>
  <value type="int">2</value>
 </data>
 <data>
  <variable>CMakeTools.Default</variable>
  <value type="QString">{fafbf8bd-e2ca-4e83-b12f-100f4196f38a}</value>
 </data>
 <data>
  <variable>Version</variable>
  <value type="int">1</value>
 </data>
</qtcreator>
